enem/__init__.py
enem/__main__.py
enem/src/__init__.py
enem/src/__main__.py
enem/src/answers.py
enem/src/image_extractor.py
enem/src/settings.py
enem/src/utils.py
enem/src/validations.py
enem-1.0.3.dist-info/LICENSE
enem-1.0.3.dist-info/METADATA
enem-1.0.3.dist-info/WHEEL
enem-1.0.3.dist-info/entry_points.txt
enem-1.0.3.dist-info/top_level.txt
enem-1.0.3.dist-info/RECORD
