Metadata-Version: 2.1
Name: enem
Version: 1.0.3
Summary: CLI Tool for ENEM PDF Extraction and JSON Export.
Home-page: https://github.com/luiisp/enem-extractor
Author: Pedro Luis Dias
Author-email: luisp.diias@gmail.com
License: MIT
Classifier: Programming Language :: Python :: 3
Classifier: Programming Language :: Python :: 3.6
Classifier: Programming Language :: Python :: 3.7
Classifier: Programming Language :: Python :: 3.8
Classifier: Programming Language :: Python :: 3.9
Classifier: Programming Language :: Python :: 3.10
Classifier: License :: OSI Approved :: MIT License
Classifier: Operating System :: OS Independent
Requires-Python: >=3.6
License-File: LICENSE
Requires-Dist: pygments
Requires-Dist: colorama
Requires-Dist: pillow
Requires-Dist: PyMuPDF
